docta_http_client/__init__.py
docta_http_client/base_client.py
docta_http_client/docta_http_client.py
docta_http_client/models.py
docta_http_client/utils.py
docta_http_client-0.1.24.dist-info/LICENSE
docta_http_client-0.1.24.dist-info/METADATA
docta_http_client-0.1.24.dist-info/WHEEL
docta_http_client-0.1.24.dist-info/top_level.txt
docta_http_client-0.1.24.dist-info/RECORD
